langjam/__init__.py
langjam/openai/__init__.py
langjam/openai/openai_function/__init__.py
langjam/openai/openai_function/openai_function.py
langjam/openai/openai_function/openai_function_model.py
langjam-0.1.7.dist-info/LICENSE
langjam-0.1.7.dist-info/METADATA
langjam-0.1.7.dist-info/WHEEL
langjam-0.1.7.dist-info/RECORD
